autobuilder/README.md
autobuilder/agent_builder.py
autobuilder/autobuilder.py
autobuilder/config.py
autobuilder/config.py_bk
autobuilder/health_check.py
autobuilder/requirements.txt
autobuilder-1.3.dist-info/METADATA
autobuilder-1.3.dist-info/WHEEL
autobuilder-1.3.dist-info/entry_points.txt
autobuilder-1.3.dist-info/top_level.txt
autobuilder-1.3.dist-info/RECORD
